eyal_lang/__init__.py
eyal_lang/__main__.py
eyal_lang/interpreter.py
eyal_lang/parser.py
eyal_lang-0.1.0.dist-info/licenses/LICENSE
tests/__init__.py
tests/test_cli.py
tests/test_interpreter.py
tests/test_parser.py
eyal_lang-0.1.0.dist-info/METADATA
eyal_lang-0.1.0.dist-info/WHEEL
eyal_lang-0.1.0.dist-info/entry_points.txt
eyal_lang-0.1.0.dist-info/top_level.txt
eyal_lang-0.1.0.dist-info/RECORD
