Metadata-Version: 2.4
Name: eyal-lang
Version: 0.1.0
Summary: A simple, rule-based DSL that interprets Eyal-style directives to Python code.
Author-email: EyalLang Contributors <eyal@example.com>
License: MIT
Project-URL: Homepage, https://github.com/Eyal-Lang/eyal-lang
Project-URL: Repository, https://github.com/Eyal-Lang/eyal-lang
Project-URL: Documentation, https://github.com/Eyal-Lang/eyal-lang#readme
Project-URL: Bug Tracker, https://github.com/Eyal-Lang/eyal-lang/issues
Keywords: dsl,interpreter,language,python,eyal
Classifier: Development Status :: 4 - Beta
Classifier: Intended Audience :: Developers
Classifier: License :: OSI Approved :: MIT License
Classifier: Operating System :: OS Independent
Classifier: Programming Language :: Python :: 3
Classifier: Programming Language :: Python :: 3.11
Classifier: Programming Language :: Python :: 3.12
Classifier: Topic :: Software Development :: Interpreters
Classifier: Topic :: Software Development :: Libraries :: Python Modules
Requires-Python: >=3.11
License-File: LICENSE
Provides-Extra: dev
Requires-Dist: pre-commit>=3.6.0; extra == "dev"
Requires-Dist: black>=23.12.0; extra == "dev"
Requires-Dist: isort>=5.13.0; extra == "dev"
Requires-Dist: mypy>=1.8.0; extra == "dev"
Requires-Dist: pylint>=3.0.0; extra == "dev"
Requires-Dist: pytest>=7.4.0; extra == "dev"
Requires-Dist: pytest-cov>=4.1.0; extra == "dev"
Dynamic: license-file
